{
  "createStepOne": {
    "headingWithIcon": {
      "title": "Hej Lasse",
      "subtitle": "Lad os få oprettet en aktivitet.",
      "iconClass": "hidden-tablet-down",
      "icon": {
        "type": "create",
        "color": "light"
      }
    },
    "progressBar": {
      "items": [
        {
          "title": "Om aktiviteten",
          "active": true
        },
        {
          "title": "Information"
        },
        {
          "title": "Kategorier"
        },
        {
          "title": "Billede"
        },
        {
          "title": "Detaljer"
        },
        {
          "title": "Bekræft"
        }
      ]
    },
    "textWithIconHeadline": {
      "title": "Vælg en overskrift og beskrivelse",
      "icon": {
        "type": "arrow",
        "class": "is-small is-green-dark", 
        "color": "light"
      }
    },
    "textWithIconParticipation": {
      "title": "Tilmeldingspligt",
      "icon": {
        "type": "arrow",
        "class": "is-small is-green-dark", 
        "color": "light"
      }
    },
    "createNavigation": {
      "buttonNext": {
        "class": "is-cta is-full-width",
        "href": "#",
        "title": "Næste"
      },
      "buttonPrev": {
        "class": "is-secondary is-dark is-full-width is-inactive",
        "href": "#",
        "title": "Tilbage"
      }
    },

    "helpBoxHeadline": {
      "title": "Hvad er en god overskrift?",
      "description": "En god overskrift er mange ting. Den kan være kort og tydelig (fx Vinsmagning i Dokk1). Den kan gøre en nysgerrig (fx Løgn og latin i sognegården) eller bruge ordspil (Luther og lagkage). Den kan love noget (Lær at binde din egen flue) eller være inviterende (Drop-ind tennis)"
    },
    
    "helpBoxDescription": {
      "title": "Hvad er en god beskrivelse?",
      "description": "En god beskrivelse fortæller lidt mere om emnet eller temaet, og hvad i skal sammen. Fx: Vi lærer om de gode råvarer fra middelhavet og laver alle retter fra bunden. Eller: Tag på en frisk cykeltur ved Moesgård med en flok motionister, der nyder den friske luft og det gode humør. Vi cykler 5 km hver gang. Hvis det er et foredrag, kan man også skrive lidt om personen, der holder foredraget. Detaljer som, hvor og hvornår det foregår, kommer vi til senere. Det samme med hvor øvet, man skal være for at kunne deltage."
    },
    
    "helpBoxParticipation": {
      "title": "Hvad er tilmeldingspligt?",
      "description": "Hvis det er vigtigt at vide, hvor mange, der kommer til din aktivitet, fordi der fx skal laves mad eller betales billetter, så sæt kryds i tilmeldingspligt."
    }

  }
}